directory_client_core/__init__.py
directory_client_core/authentication.py
directory_client_core/base.py
directory_client_core/cache_control.py
directory_client_core/helpers.py
directory_client_core-7.3.2.dist-info/licenses/LICENSE
directory_client_core-7.3.2.dist-info/METADATA
directory_client_core-7.3.2.dist-info/WHEEL
directory_client_core-7.3.2.dist-info/top_level.txt
directory_client_core-7.3.2.dist-info/RECORD
