Metadata-Version: 2.4
Name: directory_client_core
Version: 7.3.2
Summary: Python common code for Directory API clients.
Home-page: https://github.com/uktrade/directory-client-core
Author: Department for Business and Trade
License: MIT
Classifier: Development Status :: 5 - Production/Stable
Classifier: Environment :: Web Environment
Classifier: Framework :: Django
Classifier: Framework :: Django :: 1.11
Classifier: Framework :: Django :: 2.0
Classifier: Framework :: Django :: 2.1
Classifier: Framework :: Django :: 2.2
Classifier: Framework :: Django :: 3.1
Classifier: Framework :: Django :: 3.2
Classifier: Framework :: Django :: 4.2
Classifier: Intended Audience :: Developers
Classifier: License :: OSI Approved :: MIT License
Classifier: Natural Language :: English
Classifier: Operating System :: OS Independent
Classifier: Programming Language :: Python :: 3.9
Classifier: Programming Language :: Python :: 3.13
Classifier: Programming Language :: Python :: Implementation :: PyPy
Classifier: Topic :: Software Development :: Libraries :: Python Modules
License-File: LICENSE
Requires-Dist: requests<3.0.0,>=2.21.0
Requires-Dist: monotonic<3.0,>=1.2
Requires-Dist: sigauth<6.0.0,>=5.2.5
Requires-Dist: django<5.0,>=4.2.10
Requires-Dist: w3lib<2.0.0,>=1.19.0
Provides-Extra: test
Requires-Dist: flake8; extra == "test"
Requires-Dist: freezegun; extra == "test"
Requires-Dist: pytest-django<=4.11.1,>=3.8.0; extra == "test"
Requires-Dist: pytest; extra == "test"
Requires-Dist: pytest-cov; extra == "test"
Requires-Dist: pytest-codecov; extra == "test"
Requires-Dist: GitPython; extra == "test"
Requires-Dist: requests_mock==1.8.0; extra == "test"
Requires-Dist: setuptools; extra == "test"
Requires-Dist: twine; extra == "test"
Requires-Dist: wheel<1.0.0,>=0.31.0; extra == "test"
Dynamic: author
Dynamic: classifier
Dynamic: description
Dynamic: description-content-type
Dynamic: home-page
Dynamic: license
Dynamic: license-file
Dynamic: provides-extra
Dynamic: requires-dist
Dynamic: summary
